AUTHORS.md
CHANGES.md
CONTRIBUTING.md
LICENSE
MANIFEST.in
README.md
setup.cfg
setup.py
docs/404.md
docs/distributed.md
docs/gen_doc_main.md
docs/install.md
docs/performance.md
docs/support.md
docs/troubleshoot.md
docs/tutorial.resources.md
docs/tutorials.md
docs/dev/abbr.md
docs/dev/develop.md
docs/dev/git.md
docs/dev/gpu.md
docs/dev/index.md
docs/dev/release.md
docs/dev/style.md
docs/dev/test.md
docs/images/androidsdkmanagericon.png
docs/images/authorizegithubscreen2.png
docs/images/authorizeongithub.png
docs/images/company_logo.png
docs/images/company_logo_big.png
docs/images/helpapi-01.png
docs/images/illustratoroptions.png
docs/images/itermexample.png
docs/images/jekyll.png
docs/images/killalljekyll.png
docs/images/liningup.png
docs/images/workflowarrow.png
docs/imgs/betadist-mixup.png
docs/imgs/button_hide.png
docs/imgs/car_bbox.jpg
docs/imgs/car_example.jpg
docs/imgs/cat_example.jpg
docs/imgs/face_example.jpg
docs/imgs/grid.png
docs/imgs/grid_rot.png
docs/imgs/hide_input.png
docs/imgs/mask_example.png
docs/imgs/mix_match.png
docs/imgs/mixup.png
docs/imgs/nbext.png
docs/imgs/one_interpol.png
docs/imgs/onecycle_finder.png
docs/imgs/onecycle_params.png
docs/imgs/tfm_bbox.png
docs/imgs/tfm_mask.png
docs/imgs/train_graph.gif
docs/imgs/two_interpol.png
docs/imgs/u-net-architecture.png
fastai/__init__.py
fastai/basic_data.py
fastai/basic_train.py
fastai/basics.py
fastai/callback.py
fastai/collab.py
fastai/core.py
fastai/data_block.py
fastai/datasets.py
fastai/distributed.py
fastai/general_optimizer.py
fastai/launch.py
fastai/layers.py
fastai/metrics.py
fastai/script.py
fastai/sixel.py
fastai/test_registry.json
fastai/torch_core.py
fastai/train.py
fastai/version.py
fastai/callbacks/__init__.py
fastai/callbacks/csv_logger.py
fastai/callbacks/fp16.py
fastai/callbacks/general_sched.py
fastai/callbacks/hooks.py
fastai/callbacks/loss_metrics.py
fastai/callbacks/lr_finder.py
fastai/callbacks/mem.py
fastai/callbacks/misc.py
fastai/callbacks/mixup.py
fastai_bottleneck_1_1_1.egg-info/PKG-INFO
fastai_bottleneck_1_1_1.egg-info/SOURCES.txt
fastai_bottleneck_1_1_1.egg-info/dependency_links.txt
fastai_bottleneck_1_1_1.egg-info/not-zip-safe
fastai_bottleneck_1_1_1.egg-info/requires.txt
fastai_bottleneck_1_1_1.egg-info/top_level.txt
