Metadata-Version: 2.1
Name: fastai-bottleneck-1-1-1
Version: 0.3a0
Summary: This is not the official fastai package.
Home-page: https://github.com/H4dr1en/fastai
Author: Jeremy Howard
Author-email: info@fast.ai
License: Apache Software License 2.0
Download-URL: https://github.com/H4dr1en/fastai/archive/v0.3-alpha.tar.gz
Keywords: fastai,deep learning,machine learning
Platform: UNKNOWN
Classifier: Development Status :: 5 - Production/Stable
Classifier: Intended Audience :: Developers
Classifier: License :: OSI Approved :: Apache Software License
Classifier: Natural Language :: English
Classifier: Programming Language :: Python :: 3.6
Classifier: Programming Language :: Python :: 3.7
Requires-Python: >=3.6
Provides-Extra: dev
